google_dns/__init__.py
google_dns/__main__.py
google_dns-0.0.3.dist-info/LICENSE.md
google_dns-0.0.3.dist-info/METADATA
google_dns-0.0.3.dist-info/WHEEL
google_dns-0.0.3.dist-info/top_level.txt
google_dns-0.0.3.dist-info/RECORD
