Metadata-Version: 2.1
Name: google-dns
Version: 0.0.3
Summary: Google DNS
Home-page: https://github.com/JeanMaximilienCadic/ntt_google_dns
Author: Jean Maximilien Cadic
Author-email: git@cadic.jp
License: MIT
Platform: UNKNOWN
Classifier: Programming Language :: Python :: 3.6
Classifier: License :: OSI Approved :: MIT License
Requires-Python: >=3.6
License-File: LICENSE.md
Requires-Dist: gnutools-python
Requires-Dist: requests
